Workbook

Sheet Start Here
B1: Worker Classification & ABC-Test Worksheet
B2: Prepared for Tasteful Studio — to document worker classification for 2025 taxes.
B4: WHY THIS WORKSHEET EXISTS
B5: You paid several people to help with events and treated them as 1099 contractors. In California, whether someone is truly an independent contractor (1099) or an employee (W-2) is decided by the "ABC test" (Labor Code §2775 / AB 5) — not by whether they have a license. This workbook walks each person through that test so your classification is documented and defensible, and so your CPA has everything they need in one place.
B7: HOW TO USE IT (3 STEPS)
B8: STEP 1 — Payment Log tab: Enter every payment you made to a helper in 2025 (one row per payment). The Worker Classification tab totals these automatically by name, so spell each name exactly the same way.
B9: STEP 2 — Worker Classification tab: List each person once. Answer the three ABC questions (A, B, C) using the drop-downs. The sheet flags a likely classification and the likely tax form automatically.
B10: STEP 3 — Take the completed workbook to your CPA (and, if any come back "Review with CPA," an employment attorney). The flags are a guide to organize the conversation, not a final legal determination.
B12: THE ABC TEST — ALL THREE MUST BE "YES" TO BE A CONTRACTOR
B13: A — Control: Is the worker free from your direction and control over HOW the work is done? (You set the event; they decide how to do their piece.)
B14: B — Outside your business: Is the work OUTSIDE the usual course of your business? For an event-rental company, setup/teardown/staffing an event is usually INSIDE your business — which typically makes it "No" and points to employee.
B15: C — Independent business: Does the worker run their own established business doing this kind of work (own business license, own clients, own tools/insurance, advertises services)? "They don't have a license/their own business" = "No" here.
... B23: DISCLAIMER: This worksheet is an organizational tool, not tax or legal advice. Worker classification in California has real financial and legal consequences (payroll taxes, workers' comp, EDD/IRS penalties). Confirm every classification with a licensed CPA and, where appropriate, an employment attorney before filing.

Sheet Payment Log
A1: Payment Log — every payment to a helper in 2025 (one row per payment)
A2: Spell each Worker Name exactly the same way every time — the Classification tab totals by name.
A3: Date | B3: Worker Name | C3: Amount ($) | D3: Payment Method | E3: What it was for | F3: Notes
A4: 45822 | B4: Maria Lopez | C4: 450 | D4: Venmo | E4: Helped set up tents & tables at Balboa Park event | F4: EXAMPLE — overwrite
A5: 45857 | B5: Maria Lopez | C5: 300 | D5: Cash | E5: Teardown after wedding in La Jolla | F5: EXAMPLE — overwrite
A6: 45871 | B6: James Carter | C6: 700 | D6: Check #1042 | E6: Lighting setup, corporate event | F6: EXAMPLE — overwrite
B62: TOTAL LOGGED (incl. examples): | C62: =SUM(C4:C60)

Sheet Worker Classification
A1: Worker Classification — ABC test, one row per person
A2: Fill the YELLOW cells. Grey cells calculate themselves. To be a 1099 contractor, columns A, B and C must ALL be "Yes" — any "No" points to employee (W-2).
A3: Worker Name | B3: Contact (phone / email) | C3: W-9 or W-4 collected? | D3: SSN / EIN on file? | E3: Total Paid 2025 ($) | F3: First Payment | G3: Last Payment | H3: $600+ threshold? | I3: Description of work performed | J3: A — Free from your control? | K3: B — Work outside your business? | L3: C — Own established business? | M3: Own business license? | N3: Own insurance / workers' comp? | O3: LIKELY CLASSIFICATION | P3: LIKELY FORM | Q3: Notes / follow-up for CPA
A4: Maria Lopez | B4: maria@email.com / 619-555-0100 | C4: No | D4: No | E4: =IF($A4="","",SUMIF('Payment Log'!$B:$B,$A4,'Payment Log'!$C:$C)) | F4: =IF(COUNTIF('Payment Log'!$B:$B,$A4)=0,"",_xlfn.MINIFS('Payment Log'!$A:$A,'Payment Log'!$B:$B,$A4)) | G4: =IF(COUNTIF('Payment Log'!$B:$B,$A4)=0,"",_xlfn.MAXIFS('Payment Log'!$A:$A,'Payment Log'!$B:$B,$A4)) | H4: =IF($E4="","",IF($E4>=600,"Yes — reporting required","Under $600")) | I4: Set up/teardown of tents & tables at events I booked and directed | J4: No | K4: No | L4: No | M4: No | N4: No | O4: =IF(COUNTBLANK($J4:$L4)=3,"",IF(COUNTIF($J4:$L4,"No")>0,"EMPLOYEE (fails ABC test)",IF(COUNTIF($J4:$L4,"Unclear")>0,"Review with CPA",IF(COUNTIF($J4:$L4,"Yes")=3,"Possible contractor — verify","Answer all of A, B, C"))))) | P4: =IF($O4="","",IF(ISNUMBER(SEARCH("EMPLOYEE",$O4)),"W-2 (put on payroll)",IF(ISNUMBER(SEARCH("Possible contractor",$O4)),IF($E4="","1099-NEC if $600+",IF($E4>=600,"1099-NEC","No 1099 (under $600)")),"Confirm with CPA"))) | Q4: EXAMPLE — delete this row. Failed A/B/C → employee.
E5: =IF($A5="","",SUMIF('Payment Log'!$B:$B,$A5,'Payment Log'!$C:$C)) | F5: =IF(COUNTIF('Payment Log'!$B:$B,$A5)=0,"",_xlfn.MINIFS('Payment Log'!$A:$A,'Payment Log'!$B:$B,$A5)) | G5: =IF(COUNTIF('Payment Log'!$B:$B,$A5)=0,"",_xlfn.MAXIFS('Payment Log'!$A:$A,'Payment Log'!$B:$B,$A5)) | H5: =IF($E5="","",IF($E5>=600,"Yes — reporting required","Under $600")) | O5: =IF(COUNTBLANK($J5:$L5)=3,"",IF(COUNTIF($J5:$L5,"No")>0,"EMPLOYEE (fails ABC test)",IF(COUNTIF($J5:$L5,"Unclear")>0,"Review with CPA",IF(COUNTIF($J5:$L5,"Yes")=3,"Possible contractor — verify","Answer all of A, B, C"))))) | P5: =IF($O5="","",IF(ISNUMBER(SEARCH("EMPLOYEE",$O5)),"W-2 (put on payroll)",IF(ISNUMBER(SEARCH("Possible contractor",$O5)),IF($E5="","1099-NEC if $600+",IF($E5>=600,"1099-NEC","No 1099 (under $600)")),"Confirm with CPA")))
E6: =IF($A6="","",SUMIF('Payment Log'!$B:$B,$A6,'Payment Log'!$C:$C)) | F6: =IF(COUNTIF('Payment Log'!$B:$B,$A6)=0,"",_xlfn.MINIFS('Payment Log'!$A:$A,'Payment Log'!$B:$B,$A6)) | G6: =IF(COUNTIF('Payment Log'!$B:$B,$A6)=0,"",_xlfn.MAXIFS('Payment Log'!$A:$A,'Payment Log'!$B:$B,$A6)) | H6: =IF($E6="","",IF($E6>=600,"Yes — reporting required","Under $600")) | O6: =IF(COUNTBLANK($J6:$L6)=3,"",IF(COUNTIF($J6:$L6,"No")>0,"EMPLOYEE (fails ABC test)",IF(COUNTIF($J6:$L6,"Unclear")>0,"Review with CPA",IF(COUNTIF($J6:$L6,"Yes")=3,"Possible contractor — verify","Answer all of A, B, C"))))) | P6: =IF($O6="","",IF(ISNUMBER(SEARCH("EMPLOYEE",$O6)),"W-2 (put on payroll)",IF(ISNUMBER(SEARCH("Possible contractor",$O6)),IF($E6="","1099-NEC if $600+",IF($E6>=600,"1099-NEC","No 1099 (under $600)")),"Confirm with CPA")))
E7: =IF($A7="","",SUMIF('Payment Log'!$B:$B,$A7,'Payment Log'!$C:$C)) | F7: =IF(COUNTIF('Payment Log'!$B:$B,$A7)=0,"",_xlfn.MINIFS('Payment Log'!$A:$A,'Payment Log'!$B:$B,$A7)) | G7: =IF(COUNTIF('Payment Log'!$B:$B,$A7)=0,"",_xlfn.MAXIFS('Payment Log'!$A:$A,'Payment Log'!$B:$B,$A7)) | H7: =IF($E7="","",IF($E7>=600,"Yes — reporting required","Under $600")) | O7: =IF(COUNTBLANK($J7:$L7)=3,"",IF(COUNTIF($J7:$L7,"No")>0,"EMPLOYEE (fails ABC test)",IF(COUNTIF($J7:$L7,"Unclear")>0,"Review with CPA",IF(COUNTIF($J7:$L7,"Yes")=3,"Possible contractor — verify","Answer all of A, B, C"))))) | P7: =IF($O7="","",IF(ISNUMBER(SEARCH("EMPLOYEE",$O7)),"W-2 (put on payroll)",IF(ISNUMBER(SEARCH("Possible contractor",$O7)),IF($E7="","1099-NEC if $600+",IF($E7>=600,"1099-NEC","No 1099 (under $600)")),"Confirm with CPA")))
E8: =IF($A8="","",SUMIF('Payment Log'!$B:$B,$A8,'Payment Log'!$C:$C)) | F8: =IF(COUNTIF('Payment Log'!$B:$B,$A8)=0,"",_xlfn.MINIFS('Payment Log'!$A:$A,'Payment Log'!$B:$B,$A8)) | G8: =IF(COUNTIF('Payment Log'!$B:$B,$A8)=0,"",_xlfn.MAXIFS('Payment Log'!$A:$A,'Payment Log'!$B:$B,$A8)) | H8: =IF($E8="","",IF($E8>=600,"Yes — reporting required","Under $600")) | O8: =IF(COUNTBLANK($J8:$L8)=3,"",IF(COUNTIF($J8:$L8,"No")>0,"EMPLOYEE (fails ABC test)",IF(COUNTIF($J8:$L8,"Unclear")>0,"Review with CPA",IF(COUNTIF($J8:$L8,"Yes")=3,"Possible contractor — verify","Answer all of A, B, C"))))) | P8: =IF($O8="","",IF(ISNUMBER(SEARCH("EMPLOYEE",$O8)),"W-2 (put on payroll)",IF(ISNUMBER(SEARCH("Possible contractor",$O8)),IF($E8="","1099-NEC if $600+",IF($E8>=600,"1099-NEC","No 1099 (under $600)")),"Confirm with CPA")))
E9: =IF($A9="","",SUMIF('Payment Log'!$B:$B,$A9,'Payment Log'!$C:$C)) | F9: =IF(COUNTIF('Payment Log'!$B:$B,$A9)=0,"",_xlfn.MINIFS('Payment Log'!$A:$A,'Payment Log'!$B:$B,$A9)) | G9: =IF(COUNTIF('Payment Log'!$B:$B,$A9)=0,"",_xlfn.MAXIFS('Payment Log'!$A:$A,'Payment Log'!$B:$B,$A9)) | H9: =IF($E9="","",IF($E9>=600,"Yes — reporting required","Under $600")) | O9: =IF(COUNTBLANK($J9:$L9)=3,"",IF(COUNTIF($J9:$L9,"No")>0,"EMPLOYEE (fails ABC test)",IF(COUNTIF($J9:$L9,"Unclear")>0,"Review with CPA",IF(COUNTIF($J9:$L9,"Yes")=3,"Possible contractor — verify","Answer all of A, B, C"))))) | P9: =IF($O9="","",IF(ISNUMBER(SEARCH("EMPLOYEE",$O9)),"W-2 (put on payroll)",IF(ISNUMBER(SEARCH("Possible contractor",$O9)),IF($E9="","1099-NEC if $600+",IF($E9>=600,"1099-NEC","No 1099 (under $600)")),"Confirm with CPA")))
E10: =IF($A10="","",SUMIF('Payment Log'!$B:$B,$A10,'Payment Log'!$C:$C)) | F10: =IF(COUNTIF('Payment Log'!$B:$B,$A10)=0,"",_xlfn.MINIFS('Payment Log'!$A:$A,'Payment Log'!$B:$B,$A10)) | G10: =IF(COUNTIF('Payment Log'!$B:$B,$A10)=0,"",_xlfn.MAXIFS('Payment Log'!$A:$A,'Payment Log'!$B:$B,$A10)) | H10: =IF($E10="","",IF($E10>=600,"Yes — reporting required","Under $600")) | O10: =IF(COUNTBLANK($J10:$L10)=3,"",IF(COUNTIF($J10:$L10,"No")>0,"EMPLOYEE (fails ABC test)",IF(COUNTIF($J10:$L10,"Unclear")>0,"Review with CPA",IF(COUNTIF($J10:$L10,"Yes")=3,"Possible contractor — verify","Answer all of A, B, C"))))) | P10: =IF($O10="","",IF(ISNUMBER(SEARCH("EMPLOYEE",$O10)),"W-2 (put on payroll)",IF(ISNUMBER(SEARCH("Possible contractor",$O10)),IF($E10="","1099-NEC if $600+",IF($E10>=600,"1099-NEC","No 1099 (under $600)")),"Confirm with CPA")))
E11: =IF($A11="","",SUMIF('Payment Log'!$B:$B,$A11,'Payment Log'!$C:$C)) | F11: =IF(COUNTIF('Payment Log'!$B:$B,$A11)=0,"",_xlfn.MINIFS('Payment Log'!$A:$A,'Payment Log'!$B:$B,$A11)) | G11: =IF(COUNTIF('Payment Log'!$B:$B,$A11)=0,"",_xlfn.MAXIFS('Payment Log'!$A:$A,'Payment Log'!$B:$B,$A11)) | H11: =IF($E11="","",IF($E11>=600,"Yes — reporting required","Under $600")) | O11: =IF(COUNTBLANK($J11:$L11)=3,"",IF(COUNTIF($J11:$L11,"No")>0,"EMPLOYEE (fails ABC test)",IF(COUNTIF($J11:$L11,"Unclear")>0,"Review with CPA",IF(COUNTIF($J11:$L11,"Yes")=3,"Possible contractor — verify","Answer all of A, B, C"))))) | P11: =IF($O11="","",IF(ISNUMBER(SEARCH("EMPLOYEE",$O11)),"W-2 (put on payroll)",IF(ISNUMBER(SEARCH("Possible contractor",$O11)),IF($E11="","1099-NEC if $600+",IF($E11>=600,"1099-NEC","No 1099 (under $600)")),"Confirm with CPA")))
E12: =IF($A12="","",SUMIF('Payment Log'!$B:$B,$A12,'Payment Log'!$C:$C)) | F12: =IF(COUNTIF('Payment Log'!$B:$B,$A12)=0,"",_xlfn.MINIFS('Payment Log'!$A:$A,'Payment Log'!$B:$B,$A12)) | G12: =IF(COUNTIF('Payment Log'!$B:$B,$A12)=0,"",_xlfn.MAXIFS('Payment Log'!$A:$A,'Payment Log'!$B:$B,$A12)) | H12: =IF($E12="","",IF($E12>=600,"Yes — reporting required","Under $600")) | O12: =IF(COUNTBLANK($J12:$L12)=3,"",IF(COUNTIF($J12:$L12,"No")>0,"EMPLOYEE (fails ABC test)",IF(COUNTIF($J12:$L12,"Unclear")>0,"Review with CPA",IF(COUNTIF($J12:$L12,"Yes")=3,"Possible contractor — verify","Answer all of A, B, C"))))) | P12: =IF($O12="","",IF(ISNUMBER(SEARCH("EMPLOYEE",$O12)),"W-2 (put on payroll)",IF(ISNUMBER(SEARCH("Possible contractor",$O12)),IF($E12="","1099-NEC if $600+",IF($E12>=600,"1099-NEC","No 1099 (under $600)")),"Confirm with CPA")))
E13: =IF($A13="","",SUMIF('Payment Log'!$B:$B,$A13,'Payment Log'!$C:$C)) | F13: =IF(COUNTIF('Payment Log'!$B:$B,$A13)=0,"",_xlfn.MINIFS('Payment Log'!$A:$A,'Payment Log'!$B:$B,$A13)) | G13: =IF(COUNTIF('Payment Log'!$B:$B,$A13)=0,"",_xlfn.MAXIFS('Payment Log'!$A:$A,'Payment Log'!$B:$B,$A13)) | H13: =IF($E13="","",IF($E13>=600,"Yes — reporting required","Under $600")) | O13: =IF(COUNTBLANK($J13:$L13)=3,"",IF(COUNTIF($J13:$L13,"No")>0,"EMPLOYEE (fails ABC test)",IF(COUNTIF($J13:$L13,"Unclear")>0,"Review with CPA",IF(COUNTIF($J13:$L13,"Yes")=3,"Possible contractor — verify","Answer all of A, B, C"))))) | P13: =IF($O13="","",IF(ISNUMBER(SEARCH("EMPLOYEE",$O13)),"W-2 (put on payroll)",IF(ISNUMBER(SEARCH("Possible contractor",$O13)),IF($E13="","1099-NEC if $600+",IF($E13>=600,"1099-NEC","No 1099 (under $600)")),"Confirm with CPA")))
E14: =IF($A14="","",SUMIF('Payment Log'!$B:$B,$A14,'Payment Log'!$C:$C)) | F14: =IF(COUNTIF('Payment Log'!$B:$B,$A14)=0,"",_xlfn.MINIFS('Payment Log'!$A:$A,'Payment Log'!$B:$B,$A14)) | G14: =IF(COUNTIF('Payment Log'!$B:$B,$A14)=0,"",_xlfn.MAXIFS('Payment Log'!$A:$A,'Payment Log'!$B:$B,$A14)) | H14: =IF($E14="","",IF($E14>=600,"Yes — reporting required","Under $600")) | O14: =IF(COUNTBLANK($J14:$L14)=3,"",IF(COUNTIF($J14:$L14,"No")>0,"EMPLOYEE (fails ABC test)",IF(COUNTIF($J14:$L14,"Unclear")>0,"Review with CPA",IF(COUNTIF($J14:$L14,"Yes")=3,"Possible contractor — verify","Answer all of A, B, C"))))) | P14: =IF($O14="","",IF(ISNUMBER(SEARCH("EMPLOYEE",$O14)),"W-2 (put on payroll)",IF(ISNUMBER(SEARCH("Possible contractor",$O14)),IF($E14="","1099-NEC if $600+",IF($E14>=600,"1099-NEC","No 1099 (under $600)")),"Confirm with CPA")))
E15: =IF($A15="","",SUMIF('Payment Log'!$B:$B,$A15,'Payment Log'!$C:$C)) | F15: =IF(COUNTIF('Payment Log'!$B:$B,$A15)=0,"",_xlfn.MINIFS('Payment Log'!$A:$A,'Payment Log'!$B:$B,$A15)) | G15: =IF(COUNTIF('Payment Log'!$B:$B,$A15)=0,"",_xlfn.MAXIFS('Payment Log'!$A:$A,'Payment Log'!$B:$B,$A15)) | H15: =IF($E15="","",IF($E15>=600,"Yes — reporting required","Under $600")) | O15: =IF(COUNTBLANK($J15:$L15)=3,"",IF(COUNTIF($J15:$L15,"No")>0,"EMPLOYEE (fails ABC test)",IF(COUNTIF($J15:$L15,"Unclear")>0,"Review with CPA",IF(COUNTIF($J15:$L15,"Yes")=3,"Possible contractor — verify","Answer all of A, B, C"))))) | P15: =IF($O15="","",IF(ISNUMBER(SEARCH("EMPLOYEE",$O15)),"W-2 (put on payroll)",IF(ISNUMBER(SEARCH("Possible contractor",$O15)),IF($E15="","1099-NEC if $600+",IF($E15>=600,"1099-NEC","No 1099 (under $600)")),"Confirm with CPA")))
E16: =IF($A16="","",SUMIF('Payment Log'!$B:$B,$A16,'Payment Log'!$C:$C)) | F16: =IF(COUNTIF('Payment Log'!$B:$B,$A16)=0,"",_xlfn.MINIFS('Payment Log'!$A:$A,'Payment Log'!$B:$B,$A16)) | G16: =IF(COUNTIF('Payment Log'!$B:$B,$A16)=0,"",_xlfn.MAXIFS('Payment Log'!$A:$A,'Payment Log'!$B:$B,$A16)) | H16: =IF($E16="","",IF($E16>=600,"Yes — reporting required","Under $600")) | O16: =IF(COUNTBLANK($J16:$L16)=3,"",IF(COUNTIF($J16:$L16,"No")>0,"EMPLOYEE (fails ABC test)",IF(COUNTIF($J16:$L16,"Unclear")>0,"Review with CPA",IF(COUNTIF($J16:$L16,"Yes")=3,"Possible contractor — verify","Answer all of A, B, C"))))) | P16: =IF($O16="","",IF(ISNUMBER(SEARCH("EMPLOYEE",$O16)),"W-2 (put on payroll)",IF(ISNUMBER(SEARCH("Possible contractor",$O16)),IF($E16="","1099-NEC if $600+",IF($E16>=600,"1099-NEC","No 1099 (under $600)")),"Confirm with CPA")))
... E23: =IF($A23="","",SUMIF('Payment Log'!$B:$B,$A23,'Payment Log'!$C:$C)) | F23: =IF(COUNTIF('Payment Log'!$B:$B,$A23)=0,"",_xlfn.MINIFS('Payment Log'!$A:$A,'Payment Log'!$B:$B,$A23)) | G23: =IF(COUNTIF('Payment Log'!$B:$B,$A23)=0,"",_xlfn.MAXIFS('Payment Log'!$A:$A,'Payment Log'!$B:$B,$A23)) | H23: =IF($E23="","",IF($E23>=600,"Yes — reporting required","Under $600")) | O23: =IF(COUNTBLANK($J23:$L23)=3,"",IF(COUNTIF($J23:$L23,"No")>0,"EMPLOYEE (fails ABC test)",IF(COUNTIF($J23:$L23,"Unclear")>0,"Review with CPA",IF(COUNTIF($J23:$L23,"Yes")=3,"Possible contractor — verify","Answer all of A, B, C"))))) | P23: =IF($O23="","",IF(ISNUMBER(SEARCH("EMPLOYEE",$O23)),"W-2 (put on payroll)",IF(ISNUMBER(SEARCH("Possible contractor",$O23)),IF($E23="","1099-NEC if $600+",IF($E23>=600,"1099-NEC","No 1099 (under $600)")),"Confirm with CPA")))
